nametrace/__init__.py
nametrace/api.py
nametrace/data/first_names.txt
nametrace/models/__init__.py
nametrace/models/demographics.pth
nametrace/models/demographics.py
nametrace/models/human_detector.pth
nametrace/models/human_detector.py
nametrace/utils/__init__.py
nametrace/utils/data_utils.py
nametrace-0.1.1.dist-info/licenses/LICENSE
nametrace-0.1.1.dist-info/METADATA
nametrace-0.1.1.dist-info/WHEEL
nametrace-0.1.1.dist-info/top_level.txt
nametrace-0.1.1.dist-info/RECORD
