Metadata-Version: 2.4
Name: nametrace
Version: 0.1.1
Summary: Demographic prediction from name
Author-email: Paul Bose <p.bose@zoho.com>
License:                     GNU GENERAL PUBLIC LICENSE
Project-URL: Homepage, https://github.com/parobo/nametrace
Project-URL: Bug Reports, https://github.com/parobo/nametrace/issues
Project-URL: Source, https://github.com/parobo/nametrace
Keywords: name,prediction,demographics,nlp,machine-learning
Classifier: Development Status :: 3 - Alpha
Classifier: Intended Audience :: Developers
Classifier: License :: OSI Approved :: GNU General Public License v3 (GPLv3)
Classifier: Programming Language :: Python :: 3
Classifier: Programming Language :: Python :: 3.9
Classifier: Programming Language :: Python :: 3.10
Classifier: Programming Language :: Python :: 3.11
Classifier: Programming Language :: Python :: 3.12
Requires-Python: >=3.9
License-File: LICENSE
Requires-Dist: torch>=2.0.0
Requires-Dist: nameparser>=1.1.3
Dynamic: license-file
